pilotage/__init__.py
pilotage/__main__.py
pilotage/hooking/__init__.py
pilotage/hooking/ante_build_hook.py
pilotage/hooking/ante_release_hook.py
pilotage/hooking/post_build_hook.py
pilotage/hooking/post_release_hook.py
pilotage/pyrustic_data/hooking.json
pilotage/pyrustic_data/hubstore.json
pilotage/pyrustic_data/release_info.json
tests/__init__.py
pilotage-0.0.1.dist-info/LICENSE
pilotage-0.0.1.dist-info/METADATA
pilotage-0.0.1.dist-info/WHEEL
pilotage-0.0.1.dist-info/entry_points.txt
pilotage-0.0.1.dist-info/top_level.txt
pilotage-0.0.1.dist-info/RECORD
